flexcluster/__init__.py
flexcluster/impl/__init__.py
flexcluster/impl/cluster_impl.py
flexcluster/impl/tests/__init__.py
flexcluster/impl/tests/cluster_impl_test.py
flexcluster/tests/__init__.py
flexcluster/tests/cluster_test.py
flexcluster-0.0.4.dist-info/LICENSE
flexcluster-0.0.4.dist-info/METADATA
flexcluster-0.0.4.dist-info/WHEEL
flexcluster-0.0.4.dist-info/top_level.txt
flexcluster-0.0.4.dist-info/RECORD
