Metadata-Version: 2.1
Name: flexcluster
Version: 0.0.4
Summary: flexible clustering algorithm that allows user-define dissimilarity an centroid calculation
Home-page: https://github.com/hcmarchezi/flexcluster
Author: Humberto Cardoso Marchezi
Author-email: hcmarchezi@gmail.com
License: UNKNOWN
Project-URL: Bug Tracker, https://github.com/hcmarchezi/flexcluster/issues
Platform: UNKNOWN
Classifier: Programming Language :: Python :: 3
Classifier: License :: OSI Approved :: MIT License
Classifier: Operating System :: OS Independent
Requires-Python: >=3.6
License-File: LICENSE
